pgrace/__init__.py
pgrace/example.py
pgrace-0.0.2.dist-info/METADATA
pgrace-0.0.2.dist-info/WHEEL
pgrace-0.0.2.dist-info/RECORD
